vickycalculator/__init__.py
vickycalculator/calculations.py
vickycalculator-0.1.0.dist-info/LICENSE
vickycalculator-0.1.0.dist-info/METADATA
vickycalculator-0.1.0.dist-info/WHEEL
vickycalculator-0.1.0.dist-info/top_level.txt
vickycalculator-0.1.0.dist-info/RECORD
