Metadata-Version: 2.2
Name: vickycalculator
Version: 0.1.0
Summary: A Python package offering basic math calculations
Author: Vicky
Author-email: vickyvijay069@gmail.com
Classifier: Programming Language :: Python :: 3
Classifier: Operating System :: OS Independent
Requires-Python: >=3.6
License-File: LICENSE
Dynamic: author
Dynamic: author-email
Dynamic: classifier
Dynamic: description
Dynamic: description-content-type
Dynamic: requires-python
Dynamic: summary
